axiusmem/__init__.py
axiusmem/__main__.py
axiusmem/agent_utils.py
axiusmem/api.py
axiusmem/core.py
axiusmem/graphdb_adapter.py
axiusmem/orm.py
axiusmem/query_engine.py
axiusmem/temporal.py
axiusmem/user_management.py
axiusmem/utils.py
axiusmem/adapters/__init__.py
axiusmem/adapters/allegrograph_adapter.py
axiusmem/adapters/anzograph_adapter.py
axiusmem/adapters/base.py
axiusmem/adapters/blazegraph_adapter.py
axiusmem/adapters/dydra_adapter.py
axiusmem/adapters/fourstore_adapter.py
axiusmem/adapters/jena_adapter.py
axiusmem/adapters/jena_sdb_adapter.py
axiusmem/adapters/marklogic_adapter.py
axiusmem/adapters/mulgara_adapter.py
axiusmem/adapters/neptune_adapter.py
axiusmem/adapters/rdf4j_adapter.py
axiusmem/adapters/rdflib_adapter.py
axiusmem/adapters/rdfox_adapter.py
axiusmem/adapters/redland_adapter.py
axiusmem/adapters/redstore_adapter.py
axiusmem/adapters/stardog_adapter.py
axiusmem/adapters/virtuoso_adapter.py
axiusmem-1.3.0.dist-info/licenses/LICENSE
axiusmem-1.3.0.dist-info/METADATA
axiusmem-1.3.0.dist-info/WHEEL
axiusmem-1.3.0.dist-info/top_level.txt
axiusmem-1.3.0.dist-info/RECORD
