Metadata-Version: 2.4
Name: axiusmem
Version: 1.3.0
Summary: A W3C-compliant temporal knowledge graph library for AI agents.
Home-page: https://github.com/yourusername/axiusmem
Author: Timothy W. Cook
Author-email: "Timothy W. Cook" <timothywaynecook@gmail.com>
License-Expression: Apache-2.0
Requires-Python: >=3.9
License-File: LICENSE
Requires-Dist: rdflib>=6.0.0
Requires-Dist: requests>=2.25.0
Requires-Dist: pandas>=1.3.0
Requires-Dist: python-dotenv>=0.19.0
Requires-Dist: langchain>=0.1.0
Requires-Dist: langgraph>=0.0.30
Requires-Dist: openai>=1.0.0
Requires-Dist: google-generativeai>=0.3.0
Requires-Dist: anthropic>=0.21.0
Requires-Dist: cohere>=4.0.0
Requires-Dist: transformers>=4.40.0
Requires-Dist: huggingface_hub>=0.23.0
Requires-Dist: mistralai>=0.1.0
Requires-Dist: fastapi
Requires-Dist: uvicorn
Requires-Dist: bcrypt
Requires-Dist: python-jose
Dynamic: author
Dynamic: home-page
Dynamic: license-file
Dynamic: requires-python
